    [
      {
        "file": "spec/templates/methods/method_example.coffee",
        "class": {
          "className": "TestExample",
          "name": "TestExample",
          "namespace": ""
        },
        "methods": [
          {
            "doc": {
              "examples": [
                "  codo = require 'codo'\n  file = (filename, content) ->\n    console.log \"New file %s with content %s\", filename, content\n  done = (err) ->\n    if err\n      console.log \"Cannot generate documentation:\", err\n    else\n      console.log \"Documentation generated\"\n  codo.run file, done\n  "
              ],
              "comment": "<p>A method to run.</p>",
              "summary": "A method to run."
            },
            "type": "instance",
            "signature": "- (void) <strong>run</strong>()",
            "name": "run",
            "bound": false,
            "parameters": []
          }
        ],
        "variables": [],
        "properties": []
      }
    ]
